Metadata-Version: 2.4
Name: hocine7779_first_package_bis
Version: 0.1.0
Summary: A simple CLI package but an amazing one.
Requires-Dist: click==8.1.3
